cndvra8/VERSION
cndvra8/__init__.py
cndvra8/__version__.py
cndvra8/_base.py
cndvra8/vra8.py
cndvra8-0.0.1.dist-info/METADATA
cndvra8-0.0.1.dist-info/WHEEL
cndvra8-0.0.1.dist-info/top_level.txt
cndvra8-0.0.1.dist-info/RECORD
